{
    "Agriculture et alimentation":13992,
    "Aide et protection sociale":5483,
    "Banques, assurances, finance":4946,
    "Construction, logement, am\u00e9nagement du territoire":10164,
    "Culture,loisirs, tourisme, M\u00e9dias":7086,
    "Droits de l'homme et libert\u00e9s":4837,
    "Economie et finances publiques":26959,
    "Energie":2455,
    "Enseignement et recherche":5267,
    "Environnement et d\u00e9veloppement durable":14197,
    "Gouvernance et institutions publiques":3154,
    "Industries de t\u00e9l\u00e9communications et du num\u00e9rique":5056,
    "Justice et s\u00e9curit\u00e9":3278,
    "NA":596,
    "Sant\u00e9 et bien-\u00eatre":21876,
    "Transport et logistique":7119
}